mind_the_gap/__init__.py
mind_the_gap/auto_tune.py
mind_the_gap/chainage.py
mind_the_gap/mind_the_gap.py
mind_t_gap-1.0.2.dist-info/LICENSE.txt
mind_t_gap-1.0.2.dist-info/METADATA
mind_t_gap-1.0.2.dist-info/WHEEL
mind_t_gap-1.0.2.dist-info/RECORD
