Metadata-Version: 2.3
Name: mind-t-gap
Version: 1.0.2
Summary: Mind the Gap is an algorithm for detecting gaps in building footprints datasets 
Author: Jack Gonzales
Author-email: gonzalesjj@ornl.gov
Requires-Python: >=3.10,<4.0
Classifier: Programming Language :: Python :: 3
Classifier: Programming Language :: Python :: 3.10
Classifier: Programming Language :: Python :: 3.11
Classifier: Programming Language :: Python :: 3.12
Classifier: Programming Language :: Python :: 3.13
Requires-Dist: geoalchemy (>=0.7.2,<0.8.0)
Requires-Dist: geopandas (>=1.0.1,<2.0.0)
Requires-Dist: libpysal (>=4.12.1,<5.0.0)
Requires-Dist: numba (>=0.60.0,<0.61.0)
Requires-Dist: psycopg2-binary (>=2.9.10,<3.0.0)
Requires-Dist: pylint (>=3.3.6,<4.0.0)
Requires-Dist: pytest (>=8.3.4,<9.0.0)
Requires-Dist: rtree (>=1.3.0,<2.0.0)
Requires-Dist: shapely (>=2.0.6,<3.0.0)
Requires-Dist: sphinx (>=8.1.3,<9.0.0)
